zninit/__init__.py
zninit/core/__init__.py
zninit/descriptor/__init__.py
zninit-0.1.11.dist-info/LICENSE
zninit-0.1.11.dist-info/METADATA
zninit-0.1.11.dist-info/WHEEL
zninit-0.1.11.dist-info/RECORD
