Metadata-Version: 2.1
Name: zninit
Version: 0.1.11
Summary: Descriptor based dataclass implementation
License: Apache-2.0
Keywords: dataclass,descriptor
Author: zincwarecode
Author-email: zincwarecode@gmail.com
Requires-Python: >=3.8,<4.0
Classifier: License :: OSI Approved :: Apache Software License
Classifier: Programming Language :: Python :: 3
Classifier: Programming Language :: Python :: 3.8
Classifier: Programming Language :: Python :: 3.9
Classifier: Programming Language :: Python :: 3.10
Classifier: Programming Language :: Python :: 3.11
Provides-Extra: typeguard
Requires-Dist: typeguard (>=2.13.3,<3.0.0) ; extra == "typeguard"
Project-URL: repository, https://github.com/zincware/ZnInit
